aws_clamav_malware_scanner_vpc/__init__.py
aws_clamav_malware_scanner_vpc/py.typed
aws_clamav_malware_scanner_vpc/_jsii/__init__.py
aws_clamav_malware_scanner_vpc/_jsii/aws-clamav-malware-scanner-vpc@2.9.2.jsii.tgz
aws_clamav_malware_scanner_vpc-2.9.2.dist-info/LICENSE
aws_clamav_malware_scanner_vpc-2.9.2.dist-info/METADATA
aws_clamav_malware_scanner_vpc-2.9.2.dist-info/NOTICE
aws_clamav_malware_scanner_vpc-2.9.2.dist-info/WHEEL
aws_clamav_malware_scanner_vpc-2.9.2.dist-info/top_level.txt
aws_clamav_malware_scanner_vpc-2.9.2.dist-info/RECORD
